{
  "build": "py310hb7f781d_1",
  "build_number": 1,
  "channel": "https://conda.anaconda.org/conda-forge/linux-64",
  "constrains": [],
  "depends": [
    "libarrow-acero 17.0.0.*",
    "libarrow-dataset 17.0.0.*",
    "libarrow-substrait 17.0.0.*",
    "libparquet 17.0.0.*",
    "numpy >=1.19,<3",
    "pyarrow-core 17.0.0 *_1_*",
    "python >=3.10,<3.11.0a0",
    "python_abi 3.10.* *_cp310"
  ],
  "extracted_package_dir": "/home/res/miniconda3/pkgs/pyarrow-17.0.0-py310hb7f781d_1",
  "files": [],
  "fn": "pyarrow-17.0.0-py310hb7f781d_1.conda",
  "license": "Apache-2.0",
  "link": {
    "source": "/home/res/miniconda3/pkgs/pyarrow-17.0.0-py310hb7f781d_1",
    "type": 1
  },
  "md5": "e6ab07d21a111867c43fb6bd41235e31",
  "name": "pyarrow",
  "package_tarball_full_path": "/home/res/miniconda3/pkgs/pyarrow-17.0.0-py310hb7f781d_1.conda",
  "paths_data": {
    "paths": [],
    "paths_version": 1
  },
  "requested_spec": "None",
  "sha256": "14031bb305326b006ccb7fa2809b0664b391c8fba2468696aaa5672d56b33ca8",
  "size": 25704,
  "subdir": "linux-64",
  "timestamp": 1722487597000,
  "url": "https://conda.anaconda.org/conda-forge/linux-64/pyarrow-17.0.0-py310hb7f781d_1.conda",
  "version": "17.0.0"
}